servicex_analysis_utils/__init__.py
servicex_analysis_utils/cli.py
servicex_analysis_utils/dataset_resolver.py
servicex_analysis_utils/file_peeking.py
servicex_analysis_utils/materialization.py
servicex_analysis_utils-1.2.1.dist-info/METADATA
servicex_analysis_utils-1.2.1.dist-info/WHEEL
servicex_analysis_utils-1.2.1.dist-info/entry_points.txt
servicex_analysis_utils-1.2.1.dist-info/licenses/LICENSE
servicex_analysis_utils-1.2.1.dist-info/RECORD
