Metadata-Version: 2.4
Name: servicex_analysis_utils
Version: 1.2.1
Summary: A package with analysis tools for ServiceX.
Project-URL: Source Code, https://github.com/ssl-hep/ServiceX_analysis_utils
Project-URL: Issue Tracker, https://github.com/ssl-hep/ServiceX_analysis_utils/issues
Author-email: Artur Cordeiro Oudot Choi <acordeir@cern.ch>
License: BSD-3-Clause
License-File: LICENSE
Requires-Python: >=3.9
Requires-Dist: awkward>=2.6
Requires-Dist: dask-awkward>=2024.12.2
Requires-Dist: servicex
Requires-Dist: uproot>=5.0
Provides-Extra: docs
Requires-Dist: furo; extra == 'docs'
Requires-Dist: myst-parser; extra == 'docs'
Requires-Dist: sphinx-copybutton; extra == 'docs'
Requires-Dist: sphinx>=5.0; extra == 'docs'
Provides-Extra: test
Requires-Dist: miniopy-async==1.21.1; extra == 'test'
Requires-Dist: numpy>=1.21; extra == 'test'
Requires-Dist: pandas; extra == 'test'
Requires-Dist: pyarrow>=8.0.0; extra == 'test'
Requires-Dist: pytest>=7.2.0; extra == 'test'
